assetman/S3UploadThread.py
assetman/__init__.py
assetman/compile.py
assetman/compilers.py
assetman/managers.py
assetman/manifest.py
assetman/settings.py
assetman/tools.py
assetman/parsers/__init__.py
assetman/parsers/base.py
assetman/parsers/tornado_parser.py
assetman/tornadoutils/RequestHandler.py
assetman/tornadoutils/__init__.py
assetman/tornadoutils/helpers.py
assetman/tornadoutils/static.py
pyassetman-0.3.0rc5.dist-info/LICENSE
pyassetman-0.3.0rc5.dist-info/METADATA
pyassetman-0.3.0rc5.dist-info/WHEEL
pyassetman-0.3.0rc5.dist-info/top_level.txt
pyassetman-0.3.0rc5.dist-info/RECORD
